<?xml version="1.0" encoding="utf-8"?>
<clothing-items>
 <clothing>
  <id>
   679886521
  </id>
  <name>
   Lacoste Handbags Y-6529
  </name>
  <category>
   Handbags
  </category>
  <size>
   L
  </size>
  <color>
   Фиолетовый
  </color>
  <material>
   Хлопок
  </material>
  <price>
   488458
  </price>
  <rating>
   1.46
  </rating>
  <reviews>
   400273
  </reviews>
  <new>
   -
  </new>
 </clothing>
 <clothing>
  <id>
   492276080
  </id>
  <name>
   Vans Shirt W-3836
  </name>
  <category>
   Shirt
  </category>
  <size>
   XL
  </size>
  <color>
   Красный
  </color>
  <material>
   Шелк
  </material>
  <price>
   419116
  </price>
  <rating>
   2.08
  </rating>
  <reviews>
   926017
  </reviews>
  <new>
   +
  </new>
  <sporty>
   no
  </sporty>
 </clothing>
 <clothing>
  <id>
   852628800
  </id>
  <name>
   Converse Shoes J-5472
  </name>
  <category>
   Shoes
  </category>
  <size>
   M
  </size>
  <color>
   Зеленый
  </color>
  <material>
   Полиэстер
  </material>
  <price>
   101252
  </price>
  <rating>
   3.13
  </rating>
  <reviews>
   370585
  </reviews>
  <new>
   -
  </new>
  <exclusive>
   no
  </exclusive>
 </clothing>
 <clothing>
  <id>
   973710829
  </id>
  <name>
   Addidas Blouse G-5724
  </name>
  <category>
   Blouse
  </category>
  <size>
   XXL
  </size>
  <color>
   Синий
  </color>
  <material>
   Хлопок
  </material>
  <price>
   508916
  </price>
  <rating>
   4.52
  </rating>
  <reviews>
   591672
  </reviews>
  <exclusive>
   no
  </exclusive>
 </clothing>
 <clothing>
  <id>
   406218765
  </id>
  <name>
   Under Armour Belts H-1261
  </name>
  <category>
   Belts
  </category>
  <size>
   XL
  </size>
  <color>
   Красный
  </color>
  <material>
   Нейлон
  </material>
  <price>
   435121
  </price>
  <rating>
   3.32
  </rating>
  <reviews>
   104365
  </reviews>
  <new>
   -
  </new>
 </clothing>
 <clothing>
  <id>
   743366061
  </id>
  <name>
   Brooks Umbrellas C-8646
  </name>
  <category>
   Umbrellas
  </category>
  <size>
   XXL
  </size>
  <color>
   Желтый
  </color>
  <material>
   Лен
  </material>
  <price>
   406567
  </price>
  <rating>
   2.5
  </rating>
  <reviews>
   734846
  </reviews>
  <new>
   -
  </new>
  <sporty>
   no
  </sporty>
 </clothing>
 <clothing>
  <id>
   616117194
  </id>
  <name>
   Nike Belts B-6852
  </name>
  <category>
   Belts
  </category>
  <size>
   XL
  </size>
  <color>
   Оранжевый
  </color>
  <material>
   Вискоза
  </material>
  <price>
   950329
  </price>
  <rating>
   1.82
  </rating>
  <reviews>
   402492
  </reviews>
  <new>
   +
  </new>
  <sporty>
   yes
  </sporty>
 </clothing>
 <clothing>
  <id>
   408347495
  </id>
  <name>
   Converse Socks A-6402
  </name>
  <category>
   Socks
  </category>
  <size>
   L
  </size>
  <color>
   Синий
  </color>
  <material>
   Вискоза
  </material>
  <price>
   383295
  </price>
  <rating>
   2.28
  </rating>
  <reviews>
   144368
  </reviews>
  <new>
   +
  </new>
  <sporty>
   no
  </sporty>
 </clothing>
 <clothing>
  <id>
   554953054
  </id>
  <name>
   Asics Shoes A-9465
  </name>
  <category>
   Shoes
  </category>
  <size>
   XXL
  </size>
  <color>
   Зеленый
  </color>
  <material>
   Полиэстер
  </material>
  <price>
   250829
  </price>
  <rating>
   4.63
  </rating>
  <reviews>
   344648
  </reviews>
  <exclusive>
   yes
  </exclusive>
  <sporty>
   yes
  </sporty>
 </clothing>
 <clothing>
  <id>
   517516724
  </id>
  <name>
   Converse Shoes U-6253
  </name>
  <category>
   Shoes
  </category>
  <size>
   L
  </size>
  <color>
   Оранжевый
  </color>
  <material>
   Вискоза
  </material>
  <price>
   563295
  </price>
  <rating>
   1.84
  </rating>
  <reviews>
   951536
  </reviews>
  <new>
   +
  </new>
  <exclusive>
   no
  </exclusive>
 </clothing>
 <clothing>
  <id>
   166460119
  </id>
  <name>
   Converse Hat Z-9353
  </name>
  <category>
   Hat
  </category>
  <size>
   XXL
  </size>
  <color>
   Желтый
  </color>
  <material>
   Вискоза
  </material>
  <price>
   877895
  </price>
  <rating>
   3.26
  </rating>
  <reviews>
   364168
  </reviews>
  <exclusive>
   no
  </exclusive>
 </clothing>
 <clothing>
  <id>
   972757079
  </id>
  <name>
   New Balance Sweater D-8566
  </name>
  <category>
   Sweater
  </category>
  <size>
   S
  </size>
  <color>
   Фиолетовый
  </color>
  <material>
   Лен
  </material>
  <price>
   997812
  </price>
  <rating>
   4.9
  </rating>
  <reviews>
   907535
  </reviews>
  <new>
   -
  </new>
  <exclusive>
   no
  </exclusive>
  <sporty>
   no
  </sporty>
 </clothing>
 <clothing>
  <id>
   169000297
  </id>
  <name>
   DC Shirt H-6789
  </name>
  <category>
   Shirt
  </category>
  <size>
   S
  </size>
  <color>
   Красный
  </color>
  <material>
   Нейлон
  </material>
  <price>
   895376
  </price>
  <rating>
   3.33
  </rating>
  <reviews>
   196090
  </reviews>
  <new>
   -
  </new>
  <exclusive>
   no
  </exclusive>
  <sporty>
   no
  </sporty>
 </clothing>
 <clothing>
  <id>
   328965722
  </id>
  <name>
   Lacoste Shoes H-8817
  </name>
  <category>
   Shoes
  </category>
  <size>
   XXL
  </size>
  <color>
   Фиолетовый
  </color>
  <material>
   Вискоза
  </material>
  <price>
   554378
  </price>
  <rating>
   2.68
  </rating>
  <reviews>
   903128
  </reviews>
  <exclusive>
   no
  </exclusive>
  <sporty>
   yes
  </sporty>
 </clothing>
 <clothing>
  <id>
   475717429
  </id>
  <name>
   Addidas Belts F-5125
  </name>
  <category>
   Belts
  </category>
  <size>
   XXL
  </size>
  <color>
   Синий
  </color>
  <material>
   Вискоза
  </material>
  <price>
   491969
  </price>
  <rating>
   4.08
  </rating>
  <reviews>
   991801
  </reviews>
  <sporty>
   no
  </sporty>
 </clothing>
 <clothing>
  <id>
   301939751
  </id>
  <name>
   Lacoste Jeans H-7910
  </name>
  <category>
   Jeans
  </category>
  <size>
   M
  </size>
  <color>
   Зеленый
  </color>
  <material>
   Полиэстер
  </material>
  <price>
   882101
  </price>
  <rating>
   4.9
  </rating>
  <reviews>
   31935
  </reviews>
  <sporty>
   yes
  </sporty>
 </clothing>
 <clothing>
  <id>
   343615439
  </id>
  <name>
   Lacoste Umbrellas D-4573
  </name>
  <category>
   Umbrellas
  </category>
  <size>
   XXL
  </size>
  <color>
   Фиолетовый
  </color>
  <material>
   Лен
  </material>
  <price>
   743056
  </price>
  <rating>
   4.4
  </rating>
  <reviews>
   793190
  </reviews>
  <sporty>
   no
  </sporty>
 </clothing>
 <clothing>
  <id>
   957010365
  </id>
  <name>
   New Balance Hat N-6453
  </name>
  <category>
   Hat
  </category>
  <size>
   L
  </size>
  <color>
   Голубой
  </color>
  <material>
   Хлопок
  </material>
  <price>
   410716
  </price>
  <rating>
   3.01
  </rating>
  <reviews>
   747704
  </reviews>
  <exclusive>
   no
  </exclusive>
  <sporty>
   yes
  </sporty>
 </clothing>
 <clothing>
  <id>
   877605804
  </id>
  <name>
   Addidas Blouse O-5976
  </name>
  <category>
   Blouse
  </category>
  <size>
   XXL
  </size>
  <color>
   Голубой
  </color>
  <material>
   Хлопок
  </material>
  <price>
   910794
  </price>
  <rating>
   1.09
  </rating>
  <reviews>
   149940
  </reviews>
  <exclusive>
   no
  </exclusive>
  <sporty>
   no
  </sporty>
 </clothing>
 <clothing>
  <id>
   916816292
  </id>
  <name>
   Vans Pants L-8218
  </name>
  <category>
   Pants
  </category>
  <size>
   M
  </size>
  <color>
   Зеленый
  </color>
  <material>
   Вискоза
  </material>
  <price>
   617546
  </price>
  <rating>
   3.5
  </rating>
  <reviews>
   792952
  </reviews>
  <exclusive>
   yes
  </exclusive>
  <sporty>
   yes
  </sporty>
 </clothing>
 <clothing>
  <id>
   705140184
  </id>
  <name>
   Adidas Jacket J-5473
  </name>
  <category>
   Jacket
  </category>
  <size>
   XL
  </size>
  <color>
   Оранжевый
  </color>
  <material>
   Шелк
  </material>
  <price>
   838778
  </price>
  <rating>
   4.81
  </rating>
  <reviews>
   189545
  </reviews>
  <exclusive>
   no
  </exclusive>
  <sporty>
   yes
  </sporty>
 </clothing>
 <clothing>
  <id>
   803137728
  </id>
  <name>
   DC Handbags Q-1526
  </name>
  <category>
   Handbags
  </category>
  <size>
   S
  </size>
  <color>
   Зеленый
  </color>
  <material>
   Вискоза
  </material>
  <price>
   616468
  </price>
  <rating>
   3.23
  </rating>
  <reviews>
   528370
  </reviews>
  <sporty>
   yes
  </sporty>
 </clothing>
 <clothing>
  <id>
   288189662
  </id>
  <name>
   Fila T-shirt D-8846
  </name>
  <category>
   T-shirt
  </category>
  <size>
   L
  </size>
  <color>
   Оранжевый
  </color>
  <material>
   Шелк
  </material>
  <price>
   877830
  </price>
  <rating>
   3.24
  </rating>
  <reviews>
   699611
  </reviews>
  <exclusive>
   yes
  </exclusive>
 </clothing>
 <clothing>
  <id>
   203272665
  </id>
  <name>
   Addidas Jacket P-1843
  </name>
  <category>
   Jacket
  </category>
  <size>
   XXL
  </size>
  <color>
   Синий
  </color>
  <material>
   Нейлон
  </material>
  <price>
   800278
  </price>
  <rating>
   1.43
  </rating>
  <reviews>
   526766
  </reviews>
  <exclusive>
   no
  </exclusive>
  <sporty>
   no
  </sporty>
 </clothing>
 <clothing>
  <id>
   619571562
  </id>
  <name>
   PleinSport Umbrellas P-5056
  </name>
  <category>
   Umbrellas
  </category>
  <size>
   XXL
  </size>
  <color>
   Фиолетовый
  </color>
  <material>
   Вискоза
  </material>
  <price>
   572440
  </price>
  <rating>
   3.23
  </rating>
  <reviews>
   34536
  </reviews>
  <new>
   +
  </new>
  <exclusive>
   no
  </exclusive>
  <sporty>
   no
  </sporty>
 </clothing>
 <clothing>
  <id>
   704771550
  </id>
  <name>
   Asics T-shirt E-2552
  </name>
  <category>
   T-shirt
  </category>
  <size>
   XXL
  </size>
  <color>
   Красный
  </color>
  <material>
   Полиэстер
  </material>
  <price>
   296206
  </price>
  <rating>
   2.98
  </rating>
  <reviews>
   684223
  </reviews>
  <sporty>
   yes
  </sporty>
 </clothing>
 <clothing>
  <id>
   163298570
  </id>
  <name>
   Fila Blouse W-3734
  </name>
  <category>
   Blouse
  </category>
  <size>
   XL
  </size>
  <color>
   Оранжевый
  </color>
  <material>
   Шерсть
  </material>
  <price>
   865733
  </price>
  <rating>
   3.3
  </rating>
  <reviews>
   507341
  </reviews>
  <exclusive>
   yes
  </exclusive>
  <sporty>
   no
  </sporty>
 </clothing>
 <clothing>
  <id>
   843381437
  </id>
  <name>
   Adidas Pants R-3674
  </name>
  <category>
   Pants
  </category>
  <size>
   XXL
  </size>
  <color>
   Оранжевый
  </color>
  <material>
   Вискоза
  </material>
  <price>
   387021
  </price>
  <rating>
   3.69
  </rating>
  <reviews>
   374885
  </reviews>
  <exclusive>
   no
  </exclusive>
 </clothing>
 <clothing>
  <id>
   929302702
  </id>
  <name>
   Reebok Blouse D-3831
  </name>
  <category>
   Blouse
  </category>
  <size>
   M
  </size>
  <color>
   Желтый
  </color>
  <material>
   Шерсть
  </material>
  <price>
   671200
  </price>
  <rating>
   4.49
  </rating>
  <reviews>
   161662
  </reviews>
  <new>
   -
  </new>
  <exclusive>
   no
  </exclusive>
 </clothing>
 <clothing>
  <id>
   370866913
  </id>
  <name>
   Converse Belts A-3499
  </name>
  <category>
   Belts
  </category>
  <size>
   XXL
  </size>
  <color>
   Зеленый
  </color>
  <material>
   Лен
  </material>
  <price>
   453140
  </price>
  <rating>
   1.53
  </rating>
  <reviews>
   471569
  </reviews>
  <new>
   +
  </new>
 </clothing>
 <clothing>
  <id>
   129348503
  </id>
  <name>
   Reebok Belts O-9941
  </name>
  <category>
   Belts
  </category>
  <size>
   L
  </size>
  <color>
   Желтый
  </color>
  <material>
   Шерсть
  </material>
  <price>
   872425
  </price>
  <rating>
   2.42
  </rating>
  <reviews>
   391770
  </reviews>
  <new>
   +
  </new>
  <exclusive>
   no
  </exclusive>
 </clothing>
 <clothing>
  <id>
   293990203
  </id>
  <name>
   Converse Socks H-7307
  </name>
  <category>
   Socks
  </category>
  <size>
   L
  </size>
  <color>
   Голубой
  </color>
  <material>
   Вискоза
  </material>
  <price>
   785895
  </price>
  <rating>
   1.63
  </rating>
  <reviews>
   544551
  </reviews>
  <exclusive>
   no
  </exclusive>
  <sporty>
   no
  </sporty>
 </clothing>
 <clothing>
  <id>
   482239201
  </id>
  <name>
   Fila Shirt M-3305
  </name>
  <category>
   Shirt
  </category>
  <size>
   XL
  </size>
  <color>
   Красный
  </color>
  <material>
   Шелк
  </material>
  <price>
   368078
  </price>
  <rating>
   4.53
  </rating>
  <reviews>
   717539
  </reviews>
  <new>
   -
  </new>
  <exclusive>
   yes
  </exclusive>
  <sporty>
   no
  </sporty>
 </clothing>
 <clothing>
  <id>
   195031348
  </id>
  <name>
   Under Armour Gloves P-5033
  </name>
  <category>
   Gloves
  </category>
  <size>
   L
  </size>
  <color>
   Красный
  </color>
  <material>
   Вискоза
  </material>
  <price>
   625017
  </price>
  <rating>
   4.02
  </rating>
  <reviews>
   49213
  </reviews>
  <sporty>
   no
  </sporty>
 </clothing>
 <clothing>
  <id>
   312759575
  </id>
  <name>
   Reebok Socks C-7719
  </name>
  <category>
   Socks
  </category>
  <size>
   L
  </size>
  <color>
   Желтый
  </color>
  <material>
   Нейлон
  </material>
  <price>
   247177
  </price>
  <rating>
   3.65
  </rating>
  <reviews>
   46889
  </reviews>
  <new>
   -
  </new>
  <exclusive>
   yes
  </exclusive>
  <sporty>
   no
  </sporty>
 </clothing>
 <clothing>
  <id>
   195862350
  </id>
  <name>
   PleinSport T-shirt V-5612
  </name>
  <category>
   T-shirt
  </category>
  <size>
   M
  </size>
  <color>
   Голубой
  </color>
  <material>
   Кожа
  </material>
  <price>
   496861
  </price>
  <rating>
   4.19
  </rating>
  <reviews>
   129571
  </reviews>
  <exclusive>
   no
  </exclusive>
 </clothing>
 <clothing>
  <id>
   240507048
  </id>
  <name>
   Nike Socks J-8535
  </name>
  <category>
   Socks
  </category>
  <size>
   XL
  </size>
  <color>
   Синий
  </color>
  <material>
   Шерсть
  </material>
  <price>
   802009
  </price>
  <rating>
   3.46
  </rating>
  <reviews>
   280926
  </reviews>
  <sporty>
   yes
  </sporty>
 </clothing>
 <clothing>
  <id>
   930972007
  </id>
  <name>
   Adidas Umbrellas Y-3024
  </name>
  <category>
   Umbrellas
  </category>
  <size>
   XL
  </size>
  <color>
   Желтый
  </color>
  <material>
   Шерсть
  </material>
  <price>
   267938
  </price>
  <rating>
   3.65
  </rating>
  <reviews>
   312776
  </reviews>
  <new>
   -
  </new>
 </clothing>
 <clothing>
  <id>
   124362621
  </id>
  <name>
   Addidas Skirt L-8087
  </name>
  <category>
   Skirt
  </category>
  <size>
   M
  </size>
  <color>
   Зеленый
  </color>
  <material>
   Лен
  </material>
  <price>
   736469
  </price>
  <rating>
   1.57
  </rating>
  <reviews>
   276687
  </reviews>
  <new>
   -
  </new>
  <exclusive>
   yes
  </exclusive>
  <sporty>
   yes
  </sporty>
 </clothing>
</clothing-items>
