<?xml version="1.0" encoding="utf-8"?>
<clothing-items>
 <clothing>
  <id>
   377543325
  </id>
  <name>
   DC Belts T-4698
  </name>
  <category>
   Belts
  </category>
  <size>
   L
  </size>
  <color>
   Голубой
  </color>
  <material>
   Полиэстер
  </material>
  <price>
   673378
  </price>
  <rating>
   3.1
  </rating>
  <reviews>
   977608
  </reviews>
  <exclusive>
   no
  </exclusive>
  <sporty>
   no
  </sporty>
 </clothing>
 <clothing>
  <id>
   164573962
  </id>
  <name>
   Asics Jeans X-7792
  </name>
  <category>
   Jeans
  </category>
  <size>
   XL
  </size>
  <color>
   Зеленый
  </color>
  <material>
   Шерсть
  </material>
  <price>
   635654
  </price>
  <rating>
   2.29
  </rating>
  <reviews>
   323982
  </reviews>
  <exclusive>
   no
  </exclusive>
  <sporty>
   yes
  </sporty>
 </clothing>
 <clothing>
  <id>
   447176061
  </id>
  <name>
   Under Armour Pants E-2061
  </name>
  <category>
   Pants
  </category>
  <size>
   L
  </size>
  <color>
   Голубой
  </color>
  <material>
   Вискоза
  </material>
  <price>
   266946
  </price>
  <rating>
   3.14
  </rating>
  <reviews>
   517117
  </reviews>
  <exclusive>
   yes
  </exclusive>
 </clothing>
 <clothing>
  <id>
   294529175
  </id>
  <name>
   Asics Shirt C-2610
  </name>
  <category>
   Shirt
  </category>
  <size>
   M
  </size>
  <color>
   Голубой
  </color>
  <material>
   Лен
  </material>
  <price>
   760316
  </price>
  <rating>
   4.03
  </rating>
  <reviews>
   624704
  </reviews>
  <exclusive>
   yes
  </exclusive>
 </clothing>
 <clothing>
  <id>
   488067073
  </id>
  <name>
   Converse Jeans N-8703
  </name>
  <category>
   Jeans
  </category>
  <size>
   S
  </size>
  <color>
   Фиолетовый
  </color>
  <material>
   Кожа
  </material>
  <price>
   977198
  </price>
  <rating>
   2.96
  </rating>
  <reviews>
   987972
  </reviews>
  <new>
   -
  </new>
  <exclusive>
   no
  </exclusive>
 </clothing>
 <clothing>
  <id>
   917547726
  </id>
  <name>
   Lacoste Skirt V-1601
  </name>
  <category>
   Skirt
  </category>
  <size>
   S
  </size>
  <color>
   Фиолетовый
  </color>
  <material>
   Кожа
  </material>
  <price>
   287008
  </price>
  <rating>
   3.9
  </rating>
  <reviews>
   730526
  </reviews>
  <new>
   -
  </new>
  <exclusive>
   yes
  </exclusive>
 </clothing>
 <clothing>
  <id>
   792582497
  </id>
  <name>
   Addidas Shoes Z-9723
  </name>
  <category>
   Shoes
  </category>
  <size>
   XXL
  </size>
  <color>
   Синий
  </color>
  <material>
   Хлопок
  </material>
  <price>
   151116
  </price>
  <rating>
   3.66
  </rating>
  <reviews>
   905828
  </reviews>
  <exclusive>
   yes
  </exclusive>
 </clothing>
 <clothing>
  <id>
   221482275
  </id>
  <name>
   New Balance Blouse Q-1253
  </name>
  <category>
   Blouse
  </category>
  <size>
   XXL
  </size>
  <color>
   Оранжевый
  </color>
  <material>
   Нейлон
  </material>
  <price>
   745605
  </price>
  <rating>
   3.89
  </rating>
  <reviews>
   616815
  </reviews>
  <new>
   -
  </new>
  <exclusive>
   no
  </exclusive>
 </clothing>
 <clothing>
  <id>
   226829409
  </id>
  <name>
   Fila Handbags W-4854
  </name>
  <category>
   Handbags
  </category>
  <size>
   XXL
  </size>
  <color>
   Красный
  </color>
  <material>
   Нейлон
  </material>
  <price>
   749323
  </price>
  <rating>
   3.46
  </rating>
  <reviews>
   611039
  </reviews>
 </clothing>
 <clothing>
  <id>
   961365957
  </id>
  <name>
   Converse Jacket F-1684
  </name>
  <category>
   Jacket
  </category>
  <size>
   M
  </size>
  <color>
   Зеленый
  </color>
  <material>
   Шерсть
  </material>
  <price>
   598194
  </price>
  <rating>
   4.42
  </rating>
  <reviews>
   950785
  </reviews>
  <new>
   +
  </new>
 </clothing>
 <clothing>
  <id>
   385246182
  </id>
  <name>
   New Balance Shoes T-1967
  </name>
  <category>
   Shoes
  </category>
  <size>
   S
  </size>
  <color>
   Голубой
  </color>
  <material>
   Хлопок
  </material>
  <price>
   193558
  </price>
  <rating>
   3.29
  </rating>
  <reviews>
   337766
  </reviews>
  <new>
   -
  </new>
 </clothing>
 <clothing>
  <id>
   471324972
  </id>
  <name>
   Brooks Gloves O-4632
  </name>
  <category>
   Gloves
  </category>
  <size>
   XXL
  </size>
  <color>
   Синий
  </color>
  <material>
   Кожа
  </material>
  <price>
   288839
  </price>
  <rating>
   1.69
  </rating>
  <reviews>
   881152
  </reviews>
  <new>
   -
  </new>
 </clothing>
 <clothing>
  <id>
   892616422
  </id>
  <name>
   Lacoste Dress P-1097
  </name>
  <category>
   Dress
  </category>
  <size>
   XXL
  </size>
  <color>
   Желтый
  </color>
  <material>
   Вискоза
  </material>
  <price>
   622745
  </price>
  <rating>
   3.92
  </rating>
  <reviews>
   155347
  </reviews>
  <exclusive>
   no
  </exclusive>
 </clothing>
 <clothing>
  <id>
   615463200
  </id>
  <name>
   Lacoste Shoes C-5929
  </name>
  <category>
   Shoes
  </category>
  <size>
   M
  </size>
  <color>
   Зеленый
  </color>
  <material>
   Шелк
  </material>
  <price>
   495389
  </price>
  <rating>
   3.34
  </rating>
  <reviews>
   314779
  </reviews>
  <new>
   -
  </new>
  <sporty>
   no
  </sporty>
 </clothing>
 <clothing>
  <id>
   733197053
  </id>
  <name>
   Asics Umbrellas T-1916
  </name>
  <category>
   Umbrellas
  </category>
  <size>
   XL
  </size>
  <color>
   Желтый
  </color>
  <material>
   Вискоза
  </material>
  <price>
   313373
  </price>
  <rating>
   2.83
  </rating>
  <reviews>
   33911
  </reviews>
  <new>
   -
  </new>
 </clothing>
 <clothing>
  <id>
   308274804
  </id>
  <name>
   New Balance Jacket B-5252
  </name>
  <category>
   Jacket
  </category>
  <size>
   XXL
  </size>
  <color>
   Фиолетовый
  </color>
  <material>
   Кожа
  </material>
  <price>
   262949
  </price>
  <rating>
   4.19
  </rating>
  <reviews>
   134888
  </reviews>
  <new>
   -
  </new>
  <sporty>
   yes
  </sporty>
 </clothing>
 <clothing>
  <id>
   520518099
  </id>
  <name>
   New Balance Dress X-6486
  </name>
  <category>
   Dress
  </category>
  <size>
   L
  </size>
  <color>
   Оранжевый
  </color>
  <material>
   Кожа
  </material>
  <price>
   386907
  </price>
  <rating>
   2.59
  </rating>
  <reviews>
   116285
  </reviews>
  <new>
   -
  </new>
  <sporty>
   no
  </sporty>
 </clothing>
 <clothing>
  <id>
   851295893
  </id>
  <name>
   Puma Blouse K-8502
  </name>
  <category>
   Blouse
  </category>
  <size>
   L
  </size>
  <color>
   Голубой
  </color>
  <material>
   Нейлон
  </material>
  <price>
   978898
  </price>
  <rating>
   4.96
  </rating>
  <reviews>
   350364
  </reviews>
  <new>
   +
  </new>
 </clothing>
 <clothing>
  <id>
   461509589
  </id>
  <name>
   Puma Dress W-5786
  </name>
  <category>
   Dress
  </category>
  <size>
   XL
  </size>
  <color>
   Синий
  </color>
  <material>
   Лен
  </material>
  <price>
   691677
  </price>
  <rating>
   4.04
  </rating>
  <reviews>
   109562
  </reviews>
  <exclusive>
   yes
  </exclusive>
  <sporty>
   no
  </sporty>
 </clothing>
 <clothing>
  <id>
   538200395
  </id>
  <name>
   DC Hat G-8696
  </name>
  <category>
   Hat
  </category>
  <size>
   XL
  </size>
  <color>
   Фиолетовый
  </color>
  <material>
   Шерсть
  </material>
  <price>
   743957
  </price>
  <rating>
   1.8
  </rating>
  <reviews>
   247440
  </reviews>
  <new>
   -
  </new>
  <exclusive>
   yes
  </exclusive>
  <sporty>
   yes
  </sporty>
 </clothing>
 <clothing>
  <id>
   691111888
  </id>
  <name>
   Vans Jacket F-3032
  </name>
  <category>
   Jacket
  </category>
  <size>
   XXL
  </size>
  <color>
   Фиолетовый
  </color>
  <material>
   Нейлон
  </material>
  <price>
   805409
  </price>
  <rating>
   2.21
  </rating>
  <reviews>
   992966
  </reviews>
 </clothing>
 <clothing>
  <id>
   961324208
  </id>
  <name>
   Asics Pants S-7934
  </name>
  <category>
   Pants
  </category>
  <size>
   M
  </size>
  <color>
   Голубой
  </color>
  <material>
   Шерсть
  </material>
  <price>
   732925
  </price>
  <rating>
   3.49
  </rating>
  <reviews>
   97634
  </reviews>
  <new>
   +
  </new>
  <sporty>
   no
  </sporty>
 </clothing>
 <clothing>
  <id>
   847614279
  </id>
  <name>
   Fila Blouse G-1267
  </name>
  <category>
   Blouse
  </category>
  <size>
   XL
  </size>
  <color>
   Фиолетовый
  </color>
  <material>
   Вискоза
  </material>
  <price>
   801580
  </price>
  <rating>
   3.96
  </rating>
  <reviews>
   938633
  </reviews>
  <exclusive>
   no
  </exclusive>
 </clothing>
 <clothing>
  <id>
   212282573
  </id>
  <name>
   Adidas Sweater J-7839
  </name>
  <category>
   Sweater
  </category>
  <size>
   M
  </size>
  <color>
   Синий
  </color>
  <material>
   Шерсть
  </material>
  <price>
   523162
  </price>
  <rating>
   4.99
  </rating>
  <reviews>
   300692
  </reviews>
 </clothing>
 <clothing>
  <id>
   213991707
  </id>
  <name>
   Lacoste Shirt F-6290
  </name>
  <category>
   Shirt
  </category>
  <size>
   XXL
  </size>
  <color>
   Голубой
  </color>
  <material>
   Полиэстер
  </material>
  <price>
   910498
  </price>
  <rating>
   1.45
  </rating>
  <reviews>
   752941
  </reviews>
  <new>
   +
  </new>
  <sporty>
   yes
  </sporty>
 </clothing>
 <clothing>
  <id>
   859804000
  </id>
  <name>
   PleinSport Blouse X-1922
  </name>
  <category>
   Blouse
  </category>
  <size>
   XL
  </size>
  <color>
   Голубой
  </color>
  <material>
   Нейлон
  </material>
  <price>
   222237
  </price>
  <rating>
   3.54
  </rating>
  <reviews>
   675100
  </reviews>
  <new>
   -
  </new>
  <sporty>
   no
  </sporty>
 </clothing>
 <clothing>
  <id>
   282732112
  </id>
  <name>
   Asics Shirt S-2793
  </name>
  <category>
   Shirt
  </category>
  <size>
   XXL
  </size>
  <color>
   Желтый
  </color>
  <material>
   Вискоза
  </material>
  <price>
   553447
  </price>
  <rating>
   4.93
  </rating>
  <reviews>
   605173
  </reviews>
  <new>
   -
  </new>
  <exclusive>
   yes
  </exclusive>
 </clothing>
 <clothing>
  <id>
   537249223
  </id>
  <name>
   Reebok Jacket X-2220
  </name>
  <category>
   Jacket
  </category>
  <size>
   L
  </size>
  <color>
   Желтый
  </color>
  <material>
   Вискоза
  </material>
  <price>
   450441
  </price>
  <rating>
   4.98
  </rating>
  <reviews>
   84533
  </reviews>
  <new>
   -
  </new>
  <exclusive>
   yes
  </exclusive>
 </clothing>
 <clothing>
  <id>
   251696206
  </id>
  <name>
   Converse Belts E-2419
  </name>
  <category>
   Belts
  </category>
  <size>
   M
  </size>
  <color>
   Желтый
  </color>
  <material>
   Полиэстер
  </material>
  <price>
   609372
  </price>
  <rating>
   1.65
  </rating>
  <reviews>
   395394
  </reviews>
  <sporty>
   yes
  </sporty>
 </clothing>
</clothing-items>
