<?xml version="1.0" encoding="utf-8"?>
<clothing-items>
 <clothing>
  <id>
   789337666
  </id>
  <name>
   Converse Sweater R-1981
  </name>
  <category>
   Sweater
  </category>
  <size>
   S
  </size>
  <color>
   Зеленый
  </color>
  <material>
   Хлопок
  </material>
  <price>
   763913
  </price>
  <rating>
   1.77
  </rating>
  <reviews>
   794285
  </reviews>
  <new>
   -
  </new>
  <exclusive>
   no
  </exclusive>
  <sporty>
   no
  </sporty>
 </clothing>
 <clothing>
  <id>
   546773720
  </id>
  <name>
   Nike Shoes D-1159
  </name>
  <category>
   Shoes
  </category>
  <size>
   M
  </size>
  <color>
   Зеленый
  </color>
  <material>
   Кожа
  </material>
  <price>
   882608
  </price>
  <rating>
   3.96
  </rating>
  <reviews>
   484585
  </reviews>
  <new>
   -
  </new>
  <exclusive>
   no
  </exclusive>
 </clothing>
 <clothing>
  <id>
   811091737
  </id>
  <name>
   Ellesse Jacket A-7253
  </name>
  <category>
   Jacket
  </category>
  <size>
   XL
  </size>
  <color>
   Красный
  </color>
  <material>
   Вискоза
  </material>
  <price>
   528137
  </price>
  <rating>
   2.64
  </rating>
  <reviews>
   177957
  </reviews>
  <new>
   +
  </new>
 </clothing>
 <clothing>
  <id>
   969407750
  </id>
  <name>
   PleinSport Socks K-3222
  </name>
  <category>
   Socks
  </category>
  <size>
   M
  </size>
  <color>
   Оранжевый
  </color>
  <material>
   Шелк
  </material>
  <price>
   781027
  </price>
  <rating>
   1.48
  </rating>
  <reviews>
   522691
  </reviews>
  <new>
   +
  </new>
 </clothing>
 <clothing>
  <id>
   949502399
  </id>
  <name>
   Vans Shirt R-9561
  </name>
  <category>
   Shirt
  </category>
  <size>
   M
  </size>
  <color>
   Оранжевый
  </color>
  <material>
   Лен
  </material>
  <price>
   882746
  </price>
  <rating>
   4.79
  </rating>
  <reviews>
   134480
  </reviews>
  <new>
   +
  </new>
  <exclusive>
   yes
  </exclusive>
  <sporty>
   yes
  </sporty>
 </clothing>
 <clothing>
  <id>
   642930163
  </id>
  <name>
   Puma Jacket A-1463
  </name>
  <category>
   Jacket
  </category>
  <size>
   XXL
  </size>
  <color>
   Голубой
  </color>
  <material>
   Вискоза
  </material>
  <price>
   345534
  </price>
  <rating>
   4.13
  </rating>
  <reviews>
   524984
  </reviews>
  <new>
   +
  </new>
  <exclusive>
   yes
  </exclusive>
 </clothing>
 <clothing>
  <id>
   500939907
  </id>
  <name>
   Puma Belts Z-4741
  </name>
  <category>
   Belts
  </category>
  <size>
   S
  </size>
  <color>
   Желтый
  </color>
  <material>
   Лен
  </material>
  <price>
   967709
  </price>
  <rating>
   3.44
  </rating>
  <reviews>
   323962
  </reviews>
  <exclusive>
   no
  </exclusive>
  <sporty>
   no
  </sporty>
 </clothing>
 <clothing>
  <id>
   714713307
  </id>
  <name>
   Lacoste Dress G-4993
  </name>
  <category>
   Dress
  </category>
  <size>
   XL
  </size>
  <color>
   Желтый
  </color>
  <material>
   Лен
  </material>
  <price>
   228116
  </price>
  <rating>
   1.11
  </rating>
  <reviews>
   660990
  </reviews>
  <exclusive>
   no
  </exclusive>
  <sporty>
   no
  </sporty>
 </clothing>
 <clothing>
  <id>
   274928412
  </id>
  <name>
   Ellesse Jacket A-7487
  </name>
  <category>
   Jacket
  </category>
  <size>
   XL
  </size>
  <color>
   Фиолетовый
  </color>
  <material>
   Кожа
  </material>
  <price>
   448639
  </price>
  <rating>
   1.39
  </rating>
  <reviews>
   672558
  </reviews>
  <new>
   +
  </new>
  <sporty>
   no
  </sporty>
 </clothing>
 <clothing>
  <id>
   858460442
  </id>
  <name>
   Vans Umbrellas T-6380
  </name>
  <category>
   Umbrellas
  </category>
  <size>
   S
  </size>
  <color>
   Желтый
  </color>
  <material>
   Вискоза
  </material>
  <price>
   207407
  </price>
  <rating>
   3.64
  </rating>
  <reviews>
   234281
  </reviews>
  <exclusive>
   yes
  </exclusive>
  <sporty>
   no
  </sporty>
 </clothing>
 <clothing>
  <id>
   563111679
  </id>
  <name>
   Lacoste Gloves X-7311
  </name>
  <category>
   Gloves
  </category>
  <size>
   S
  </size>
  <color>
   Желтый
  </color>
  <material>
   Полиэстер
  </material>
  <price>
   721245
  </price>
  <rating>
   3.37
  </rating>
  <reviews>
   884435
  </reviews>
  <exclusive>
   yes
  </exclusive>
  <sporty>
   no
  </sporty>
 </clothing>
 <clothing>
  <id>
   304709986
  </id>
  <name>
   Brooks T-shirt R-2924
  </name>
  <category>
   T-shirt
  </category>
  <size>
   S
  </size>
  <color>
   Голубой
  </color>
  <material>
   Нейлон
  </material>
  <price>
   726514
  </price>
  <rating>
   1.58
  </rating>
  <reviews>
   248210
  </reviews>
  <exclusive>
   yes
  </exclusive>
 </clothing>
 <clothing>
  <id>
   581461259
  </id>
  <name>
   Under Armour Shoes J-3534
  </name>
  <category>
   Shoes
  </category>
  <size>
   M
  </size>
  <color>
   Оранжевый
  </color>
  <material>
   Шелк
  </material>
  <price>
   613647
  </price>
  <rating>
   4.0
  </rating>
  <reviews>
   833749
  </reviews>
  <new>
   -
  </new>
  <exclusive>
   no
  </exclusive>
  <sporty>
   yes
  </sporty>
 </clothing>
 <clothing>
  <id>
   220461546
  </id>
  <name>
   Brooks Pants Z-3980
  </name>
  <category>
   Pants
  </category>
  <size>
   XXL
  </size>
  <color>
   Оранжевый
  </color>
  <material>
   Шелк
  </material>
  <price>
   551504
  </price>
  <rating>
   1.25
  </rating>
  <reviews>
   934614
  </reviews>
  <exclusive>
   no
  </exclusive>
 </clothing>
 <clothing>
  <id>
   428506824
  </id>
  <name>
   Under Armour T-shirt B-6865
  </name>
  <category>
   T-shirt
  </category>
  <size>
   M
  </size>
  <color>
   Желтый
  </color>
  <material>
   Полиэстер
  </material>
  <price>
   142108
  </price>
  <rating>
   4.0
  </rating>
  <reviews>
   417656
  </reviews>
  <new>
   -
  </new>
  <exclusive>
   yes
  </exclusive>
  <sporty>
   no
  </sporty>
 </clothing>
 <clothing>
  <id>
   322169764
  </id>
  <name>
   Nike Umbrellas G-7187
  </name>
  <category>
   Umbrellas
  </category>
  <size>
   S
  </size>
  <color>
   Зеленый
  </color>
  <material>
   Шелк
  </material>
  <price>
   417993
  </price>
  <rating>
   3.22
  </rating>
  <reviews>
   469028
  </reviews>
  <exclusive>
   no
  </exclusive>
 </clothing>
 <clothing>
  <id>
   778927023
  </id>
  <name>
   Addidas Shoes N-9296
  </name>
  <category>
   Shoes
  </category>
  <size>
   M
  </size>
  <color>
   Оранжевый
  </color>
  <material>
   Шелк
  </material>
  <price>
   641221
  </price>
  <rating>
   4.77
  </rating>
  <reviews>
   697242
  </reviews>
  <exclusive>
   no
  </exclusive>
 </clothing>
 <clothing>
  <id>
   793475278
  </id>
  <name>
   Brooks Gloves Y-3408
  </name>
  <category>
   Gloves
  </category>
  <size>
   XL
  </size>
  <color>
   Синий
  </color>
  <material>
   Шелк
  </material>
  <price>
   541366
  </price>
  <rating>
   1.39
  </rating>
  <reviews>
   273910
  </reviews>
  <exclusive>
   no
  </exclusive>
  <sporty>
   no
  </sporty>
 </clothing>
 <clothing>
  <id>
   234191081
  </id>
  <name>
   Converse Dress I-7762
  </name>
  <category>
   Dress
  </category>
  <size>
   XL
  </size>
  <color>
   Синий
  </color>
  <material>
   Хлопок
  </material>
  <price>
   735516
  </price>
  <rating>
   4.67
  </rating>
  <reviews>
   293700
  </reviews>
  <new>
   +
  </new>
  <sporty>
   no
  </sporty>
 </clothing>
 <clothing>
  <id>
   788753011
  </id>
  <name>
   New Balance Handbags Y-6796
  </name>
  <category>
   Handbags
  </category>
  <size>
   XL
  </size>
  <color>
   Синий
  </color>
  <material>
   Кожа
  </material>
  <price>
   351665
  </price>
  <rating>
   3.2
  </rating>
  <reviews>
   765270
  </reviews>
  <new>
   -
  </new>
  <sporty>
   no
  </sporty>
 </clothing>
 <clothing>
  <id>
   155604174
  </id>
  <name>
   Addidas Umbrellas T-3738
  </name>
  <category>
   Umbrellas
  </category>
  <size>
   L
  </size>
  <color>
   Синий
  </color>
  <material>
   Нейлон
  </material>
  <price>
   211543
  </price>
  <rating>
   4.64
  </rating>
  <reviews>
   407144
  </reviews>
  <new>
   -
  </new>
 </clothing>
 <clothing>
  <id>
   693578222
  </id>
  <name>
   Adidas Handbags I-8553
  </name>
  <category>
   Handbags
  </category>
  <size>
   XL
  </size>
  <color>
   Красный
  </color>
  <material>
   Шерсть
  </material>
  <price>
   962092
  </price>
  <rating>
   1.81
  </rating>
  <reviews>
   675229
  </reviews>
  <new>
   +
  </new>
  <sporty>
   no
  </sporty>
 </clothing>
 <clothing>
  <id>
   810124963
  </id>
  <name>
   DC Pants K-3781
  </name>
  <category>
   Pants
  </category>
  <size>
   XL
  </size>
  <color>
   Оранжевый
  </color>
  <material>
   Хлопок
  </material>
  <price>
   397074
  </price>
  <rating>
   4.04
  </rating>
  <reviews>
   938013
  </reviews>
  <new>
   -
  </new>
 </clothing>
 <clothing>
  <id>
   974524470
  </id>
  <name>
   Nike Shoes F-9285
  </name>
  <category>
   Shoes
  </category>
  <size>
   XL
  </size>
  <color>
   Голубой
  </color>
  <material>
   Полиэстер
  </material>
  <price>
   932261
  </price>
  <rating>
   4.88
  </rating>
  <reviews>
   608498
  </reviews>
  <new>
   -
  </new>
  <exclusive>
   no
  </exclusive>
  <sporty>
   yes
  </sporty>
 </clothing>
 <clothing>
  <id>
   322418543
  </id>
  <name>
   Reebok Skirt Y-8630
  </name>
  <category>
   Skirt
  </category>
  <size>
   L
  </size>
  <color>
   Желтый
  </color>
  <material>
   Шерсть
  </material>
  <price>
   269563
  </price>
  <rating>
   3.01
  </rating>
  <reviews>
   504922
  </reviews>
  <new>
   +
  </new>
  <sporty>
   no
  </sporty>
 </clothing>
 <clothing>
  <id>
   147268489
  </id>
  <name>
   Asics Hat Z-1439
  </name>
  <category>
   Hat
  </category>
  <size>
   L
  </size>
  <color>
   Синий
  </color>
  <material>
   Шелк
  </material>
  <price>
   437952
  </price>
  <rating>
   1.81
  </rating>
  <reviews>
   665905
  </reviews>
  <exclusive>
   yes
  </exclusive>
 </clothing>
 <clothing>
  <id>
   536831284
  </id>
  <name>
   DC Shoes V-1935
  </name>
  <category>
   Shoes
  </category>
  <size>
   M
  </size>
  <color>
   Фиолетовый
  </color>
  <material>
   Шелк
  </material>
  <price>
   570942
  </price>
  <rating>
   3.09
  </rating>
  <reviews>
   414768
  </reviews>
  <exclusive>
   no
  </exclusive>
  <sporty>
   no
  </sporty>
 </clothing>
 <clothing>
  <id>
   763802243
  </id>
  <name>
   Fila Jacket T-6942
  </name>
  <category>
   Jacket
  </category>
  <size>
   M
  </size>
  <color>
   Голубой
  </color>
  <material>
   Полиэстер
  </material>
  <price>
   133473
  </price>
  <rating>
   2.03
  </rating>
  <reviews>
   191455
  </reviews>
  <new>
   -
  </new>
  <sporty>
   no
  </sporty>
 </clothing>
 <clothing>
  <id>
   860932010
  </id>
  <name>
   Asics Blouse O-9954
  </name>
  <category>
   Blouse
  </category>
  <size>
   L
  </size>
  <color>
   Голубой
  </color>
  <material>
   Нейлон
  </material>
  <price>
   693345
  </price>
  <rating>
   2.99
  </rating>
  <reviews>
   20501
  </reviews>
  <exclusive>
   no
  </exclusive>
 </clothing>
 <clothing>
  <id>
   122699033
  </id>
  <name>
   Addidas Pants I-4207
  </name>
  <category>
   Pants
  </category>
  <size>
   M
  </size>
  <color>
   Красный
  </color>
  <material>
   Шерсть
  </material>
  <price>
   732150
  </price>
  <rating>
   1.47
  </rating>
  <reviews>
   511871
  </reviews>
  <new>
   -
  </new>
  <exclusive>
   no
  </exclusive>
  <sporty>
   no
  </sporty>
 </clothing>
 <clothing>
  <id>
   975929359
  </id>
  <name>
   Fila Blouse O-2697
  </name>
  <category>
   Blouse
  </category>
  <size>
   L
  </size>
  <color>
   Синий
  </color>
  <material>
   Нейлон
  </material>
  <price>
   269472
  </price>
  <rating>
   2.26
  </rating>
  <reviews>
   703219
  </reviews>
  <sporty>
   no
  </sporty>
 </clothing>
 <clothing>
  <id>
   186059260
  </id>
  <name>
   Addidas Dress C-9524
  </name>
  <category>
   Dress
  </category>
  <size>
   M
  </size>
  <color>
   Зеленый
  </color>
  <material>
   Нейлон
  </material>
  <price>
   379912
  </price>
  <rating>
   2.6
  </rating>
  <reviews>
   781556
  </reviews>
  <exclusive>
   no
  </exclusive>
  <sporty>
   no
  </sporty>
 </clothing>
 <clothing>
  <id>
   692637690
  </id>
  <name>
   Brooks Handbags Q-7551
  </name>
  <category>
   Handbags
  </category>
  <size>
   XXL
  </size>
  <color>
   Желтый
  </color>
  <material>
   Нейлон
  </material>
  <price>
   146716
  </price>
  <rating>
   4.44
  </rating>
  <reviews>
   873558
  </reviews>
  <new>
   +
  </new>
  <exclusive>
   no
  </exclusive>
  <sporty>
   no
  </sporty>
 </clothing>
 <clothing>
  <id>
   801229619
  </id>
  <name>
   PleinSport Belts F-5238
  </name>
  <category>
   Belts
  </category>
  <size>
   L
  </size>
  <color>
   Красный
  </color>
  <material>
   Шерсть
  </material>
  <price>
   784960
  </price>
  <rating>
   3.33
  </rating>
  <reviews>
   82815
  </reviews>
  <exclusive>
   no
  </exclusive>
  <sporty>
   yes
  </sporty>
 </clothing>
 <clothing>
  <id>
   231310892
  </id>
  <name>
   Vans Handbags W-2669
  </name>
  <category>
   Handbags
  </category>
  <size>
   L
  </size>
  <color>
   Зеленый
  </color>
  <material>
   Шелк
  </material>
  <price>
   895802
  </price>
  <rating>
   2.95
  </rating>
  <reviews>
   646688
  </reviews>
  <exclusive>
   no
  </exclusive>
  <sporty>
   yes
  </sporty>
 </clothing>
 <clothing>
  <id>
   194524837
  </id>
  <name>
   Adidas Gloves O-3397
  </name>
  <category>
   Gloves
  </category>
  <size>
   L
  </size>
  <color>
   Синий
  </color>
  <material>
   Шерсть
  </material>
  <price>
   244881
  </price>
  <rating>
   1.98
  </rating>
  <reviews>
   923828
  </reviews>
  <exclusive>
   yes
  </exclusive>
 </clothing>
 <clothing>
  <id>
   529313940
  </id>
  <name>
   Converse Pants T-7572
  </name>
  <category>
   Pants
  </category>
  <size>
   L
  </size>
  <color>
   Зеленый
  </color>
  <material>
   Шелк
  </material>
  <price>
   679124
  </price>
  <rating>
   1.15
  </rating>
  <reviews>
   378053
  </reviews>
  <new>
   -
  </new>
  <exclusive>
   no
  </exclusive>
  <sporty>
   no
  </sporty>
 </clothing>
 <clothing>
  <id>
   514779612
  </id>
  <name>
   New Balance Handbags Z-1518
  </name>
  <category>
   Handbags
  </category>
  <size>
   S
  </size>
  <color>
   Голубой
  </color>
  <material>
   Хлопок
  </material>
  <price>
   771309
  </price>
  <rating>
   1.64
  </rating>
  <reviews>
   579342
  </reviews>
  <new>
   +
  </new>
  <exclusive>
   no
  </exclusive>
  <sporty>
   no
  </sporty>
 </clothing>
 <clothing>
  <id>
   286390054
  </id>
  <name>
   PleinSport Handbags Y-9515
  </name>
  <category>
   Handbags
  </category>
  <size>
   XXL
  </size>
  <color>
   Оранжевый
  </color>
  <material>
   Шелк
  </material>
  <price>
   460737
  </price>
  <rating>
   4.81
  </rating>
  <reviews>
   98652
  </reviews>
  <new>
   +
  </new>
  <exclusive>
   yes
  </exclusive>
 </clothing>
 <clothing>
  <id>
   526268545
  </id>
  <name>
   Lacoste Pants C-1391
  </name>
  <category>
   Pants
  </category>
  <size>
   L
  </size>
  <color>
   Желтый
  </color>
  <material>
   Шелк
  </material>
  <price>
   156574
  </price>
  <rating>
   3.86
  </rating>
  <reviews>
   936517
  </reviews>
  <sporty>
   no
  </sporty>
 </clothing>
 <clothing>
  <id>
   755384450
  </id>
  <name>
   Adidas Shirt X-4906
  </name>
  <category>
   Shirt
  </category>
  <size>
   XL
  </size>
  <color>
   Голубой
  </color>
  <material>
   Лен
  </material>
  <price>
   128512
  </price>
  <rating>
   1.8
  </rating>
  <reviews>
   849878
  </reviews>
  <new>
   -
  </new>
  <exclusive>
   no
  </exclusive>
 </clothing>
 <clothing>
  <id>
   826201157
  </id>
  <name>
   Asics Pants J-1873
  </name>
  <category>
   Pants
  </category>
  <size>
   XL
  </size>
  <color>
   Красный
  </color>
  <material>
   Вискоза
  </material>
  <price>
   208213
  </price>
  <rating>
   4.37
  </rating>
  <reviews>
   689556
  </reviews>
  <new>
   -
  </new>
 </clothing>
 <clothing>
  <id>
   233309654
  </id>
  <name>
   Puma Belts K-9599
  </name>
  <category>
   Belts
  </category>
  <size>
   L
  </size>
  <color>
   Зеленый
  </color>
  <material>
   Кожа
  </material>
  <price>
   783294
  </price>
  <rating>
   2.21
  </rating>
  <reviews>
   866822
  </reviews>
  <new>
   +
  </new>
  <exclusive>
   no
  </exclusive>
  <sporty>
   no
  </sporty>
 </clothing>
 <clothing>
  <id>
   816517826
  </id>
  <name>
   Reebok Gloves P-8831
  </name>
  <category>
   Gloves
  </category>
  <size>
   XXL
  </size>
  <color>
   Желтый
  </color>
  <material>
   Кожа
  </material>
  <price>
   139882
  </price>
  <rating>
   2.64
  </rating>
  <reviews>
   804789
  </reviews>
 </clothing>
 <clothing>
  <id>
   235528590
  </id>
  <name>
   Nike Hat X-9424
  </name>
  <category>
   Hat
  </category>
  <size>
   XL
  </size>
  <color>
   Красный
  </color>
  <material>
   Вискоза
  </material>
  <price>
   515573
  </price>
  <rating>
   3.09
  </rating>
  <reviews>
   271316
  </reviews>
  <new>
   -
  </new>
 </clothing>
</clothing-items>
