[
    {
        "_id": "Мадрид",
        "max_age": "65",
        "min_age": "24",
        "avg_age": "47.54545454545455"
    },
    {
        "_id": "Картахена",
        "max_age": "62",
        "min_age": "28",
        "avg_age": "46.30769230769231"
    },
    {
        "_id": "Эль-Пуэрто-де-Санта-Мария",
        "max_age": "63",
        "min_age": "18",
        "avg_age": "44.27272727272727"
    },
    {
        "_id": "Семана",
        "max_age": "57",
        "min_age": "20",
        "avg_age": "35.07142857142857"
    },
    {
        "_id": "Будапешт",
        "max_age": "57",
        "min_age": "24",
        "avg_age": "42.266666666666666"
    },
    {
        "_id": "Льейда",
        "max_age": "64",
        "min_age": "21",
        "avg_age": "47.611111111111114"
    },
    {
        "_id": "Валенсия",
        "max_age": "65",
        "min_age": "22",
        "avg_age": "38.15384615384615"
    },
    {
        "_id": "Авилес",
        "max_age": "63",
        "min_age": "21",
        "avg_age": "43.0"
    },
    {
        "_id": "Эльче",
        "max_age": "60",
        "min_age": "21",
        "avg_age": "42.46666666666667"
    },
    {
        "_id": "Мурсия",
        "max_age": "64",
        "min_age": "25",
        "avg_age": "42.46666666666667"
    },
    {
        "_id": "Мартоса",
        "max_age": "64",
        "min_age": "19",
        "avg_age": "39.3125"
    },
    {
        "_id": "Артейхо",
        "max_age": "65",
        "min_age": "19",
        "avg_age": "41.416666666666664"
    },
    {
        "_id": "Ташкент",
        "max_age": "65",
        "min_age": "20",
        "avg_age": "44.6875"
    },
    {
        "_id": "Касерес",
        "max_age": "58",
        "min_age": "18",
        "avg_age": "38.46153846153846"
    },
    {
        "_id": "Сория",
        "max_age": "64",
        "min_age": "18",
        "avg_age": "40.6875"
    },
    {
        "_id": "Махадаонда",
        "max_age": "65",
        "min_age": "29",
        "avg_age": "49.86666666666667"
    },
    {
        "_id": "Хихон",
        "max_age": "65",
        "min_age": "18",
        "avg_age": "42.714285714285715"
    },
    {
        "_id": "Москва",
        "max_age": "61",
        "min_age": "24",
        "avg_age": "38.86666666666667"
    },
    {
        "_id": "Афины",
        "max_age": "62",
        "min_age": "20",
        "avg_age": "35.625"
    },
    {
        "_id": "Сантьяго-де-Компостела",
        "max_age": "52",
        "min_age": "18",
        "avg_age": "31.2"
    },
    {
        "_id": "Тирана",
        "max_age": "65",
        "min_age": "18",
        "avg_age": "38.10526315789474"
    },
    {
        "_id": "Алькала-де-Энарес",
        "max_age": "61",
        "min_age": "23",
        "avg_age": "43.75"
    },
    {
        "_id": "Астана",
        "max_age": "56",
        "min_age": "23",
        "avg_age": "42.857142857142854"
    },
    {
        "_id": "Куэнка",
        "max_age": "48",
        "min_age": "21",
        "avg_age": "32.90909090909091"
    },
    {
        "_id": "Рига",
        "max_age": "55",
        "min_age": "18",
        "avg_age": "39.470588235294116"
    },
    {
        "_id": "Гранада",
        "max_age": "63",
        "min_age": "23",
        "avg_age": "39.90909090909091"
    },
    {
        "_id": "Аликанте",
        "max_age": "64",
        "min_age": "18",
        "avg_age": "40.285714285714285"
    },
    {
        "_id": "Мерида",
        "max_age": "62",
        "min_age": "18",
        "avg_age": "38.57142857142857"
    },
    {
        "_id": "Краков",
        "max_age": "64",
        "min_age": "19",
        "avg_age": "39.529411764705884"
    },
    {
        "_id": "Севилья",
        "max_age": "64",
        "min_age": "22",
        "avg_age": "41.95454545454545"
    },
    {
        "_id": "Кордова",
        "max_age": "65",
        "min_age": "18",
        "avg_age": "41.705882352941174"
    },
    {
        "_id": "Лас-Росас",
        "max_age": "64",
        "min_age": "18",
        "avg_age": "41.333333333333336"
    },
    {
        "_id": "Бильбао",
        "max_age": "64",
        "min_age": "18",
        "avg_age": "42.9375"
    },
    {
        "_id": "Вальядолид",
        "max_age": "65",
        "min_age": "22",
        "avg_age": "46.0"
    },
    {
        "_id": "Кишинев",
        "max_age": "55",
        "min_age": "24",
        "avg_age": "37.357142857142854"
    },
    {
        "_id": "Санхенхо",
        "max_age": "64",
        "min_age": "18",
        "avg_age": "41.72727272727273"
    },
    {
        "_id": "Любляна",
        "max_age": "64",
        "min_age": "19",
        "avg_age": "42.06666666666667"
    },
    {
        "_id": "Вильнюс",
        "max_age": "65",
        "min_age": "18",
        "avg_age": "46.08695652173913"
    },
    {
        "_id": "Фигерас",
        "max_age": "58",
        "min_age": "24",
        "avg_age": "43.833333333333336"
    },
    {
        "_id": "Прага",
        "max_age": "64",
        "min_age": "19",
        "avg_age": "47.0"
    },
    {
        "_id": "Сан-Себастьян",
        "max_age": "61",
        "min_age": "21",
        "avg_age": "38.2"
    },
    {
        "_id": "Подгорица",
        "max_age": "61",
        "min_age": "19",
        "avg_age": "40.0"
    },
    {
        "_id": "Таллин",
        "max_age": "64",
        "min_age": "19",
        "avg_age": "36.75"
    },
    {
        "_id": "Алма-Ата",
        "max_age": "63",
        "min_age": "18",
        "avg_age": "34.88461538461539"
    },
    {
        "_id": "Пласенсия",
        "max_age": "62",
        "min_age": "19",
        "avg_age": "41.57142857142857"
    },
    {
        "_id": "Осера",
        "max_age": "58",
        "min_age": "19",
        "avg_age": "32.69565217391305"
    },
    {
        "_id": "Ла-Корунья",
        "max_age": "65",
        "min_age": "18",
        "avg_age": "41.5"
    },
    {
        "_id": "Вроцлав",
        "max_age": "63",
        "min_age": "18",
        "avg_age": "35.0"
    },
    {
        "_id": "Минск",
        "max_age": "65",
        "min_age": "19",
        "avg_age": "41.916666666666664"
    },
    {
        "_id": "Виго",
        "max_age": "63",
        "min_age": "24",
        "avg_age": "46.25"
    },
    {
        "_id": "Варшава",
        "max_age": "64",
        "min_age": "24",
        "avg_age": "45.31578947368421"
    },
    {
        "_id": "Тбилиси",
        "max_age": "64",
        "min_age": "19",
        "avg_age": "40.0"
    },
    {
        "_id": "Кадакес",
        "max_age": "55",
        "min_age": "18",
        "avg_age": "34.81818181818182"
    },
    {
        "_id": "Овьедо",
        "max_age": "64",
        "min_age": "20",
        "avg_age": "38.23529411764706"
    },
    {
        "_id": "Навалькарнеро",
        "max_age": "62",
        "min_age": "19",
        "avg_age": "40.2"
    },
    {
        "_id": "Трухильо",
        "max_age": "63",
        "min_age": "19",
        "avg_age": "39.0"
    },
    {
        "_id": "Бургос",
        "max_age": "64",
        "min_age": "18",
        "avg_age": "46.54545454545455"
    },
    {
        "_id": "Самора",
        "max_age": "65",
        "min_age": "19",
        "avg_age": "41.5"
    },
    {
        "_id": "Тарраса",
        "max_age": "56",
        "min_age": "19",
        "avg_age": "40.4"
    },
    {
        "_id": "Камбадос",
        "max_age": "64",
        "min_age": "24",
        "avg_age": "43.1"
    },
    {
        "_id": "Барселона",
        "max_age": "65",
        "min_age": "20",
        "avg_age": "36.30769230769231"
    },
    {
        "_id": "Луарка",
        "max_age": "63",
        "min_age": "18",
        "avg_age": "41.8235294117647"
    },
    {
        "_id": "Тудела",
        "max_age": "65",
        "min_age": "18",
        "avg_age": "42.94117647058823"
    },
    {
        "_id": "Ереван",
        "max_age": "61",
        "min_age": "25",
        "avg_age": "43.6"
    },
    {
        "_id": "Монсон",
        "max_age": "65",
        "min_age": "23",
        "avg_age": "39.411764705882355"
    },
    {
        "_id": "Сьюдад-Реаль",
        "max_age": "50",
        "min_age": "18",
        "avg_age": "32.42857142857143"
    },
    {
        "_id": "Вильявисиоса",
        "max_age": "62",
        "min_age": "20",
        "avg_age": "36.69230769230769"
    },
    {
        "_id": "Загреб",
        "max_age": "56",
        "min_age": "27",
        "avg_age": "42.333333333333336"
    },
    {
        "_id": "Бланес",
        "max_age": "58",
        "min_age": "24",
        "avg_age": "46.083333333333336"
    },
    {
        "_id": "Луго",
        "max_age": "65",
        "min_age": "20",
        "avg_age": "41.904761904761905"
    },
    {
        "_id": "Санкт-Петербург",
        "max_age": "65",
        "min_age": "19",
        "avg_age": "43.142857142857146"
    },
    {
        "_id": "Белград",
        "max_age": "63",
        "min_age": "29",
        "avg_age": "43.56"
    },
    {
        "_id": "Малага",
        "max_age": "64",
        "min_age": "22",
        "avg_age": "40.92857142857143"
    },
    {
        "_id": "Баку",
        "max_age": "65",
        "min_age": "26",
        "avg_age": "47.714285714285715"
    },
    {
        "_id": "Бишкек",
        "max_age": "54",
        "min_age": "29",
        "avg_age": "43.714285714285715"
    },
    {
        "_id": "Сеговия",
        "max_age": "63",
        "min_age": "18",
        "avg_age": "40.63636363636363"
    },
    {
        "_id": "Сараево",
        "max_age": "60",
        "min_age": "38",
        "avg_age": "49.92307692307692"
    },
    {
        "_id": "Душанбе",
        "max_age": "63",
        "min_age": "20",
        "avg_age": "41.8"
    },
    {
        "_id": "Скопье",
        "max_age": "65",
        "min_age": "19",
        "avg_age": "38.4375"
    },
    {
        "_id": "София",
        "max_age": "65",
        "min_age": "20",
        "avg_age": "46.05882352941177"
    },
    {
        "_id": "Хельсинки",
        "max_age": "53",
        "min_age": "19",
        "avg_age": "40.733333333333334"
    }
]